{
  "object": "card",
  "id": "aba51852-af8f-49d8-8fb6-22d52a1742b8",
  "oracle_id": "c8de43a3-ebd3-4000-b343-a6ffed11d34d",
  "multiverse_ids": [
    522242
  ],
  "mtgo_id": 90709,
  "tcgplayer_id": 239801,
  "cardmarket_id": 566365,
  "name": "Ignoble Hierarch",
  "lang": "en",
  "released_at": "2021-06-18",
  "uri": "https://api.scryfall.com/cards/aba51852-af8f-49d8-8fb6-22d52a1742b8",
  "scryfall_uri": "https://scryfall.com/card/mh2/166/ignoble-hierarch?utm_source=api",
  "layout": "normal",
  "highres_image": true,
  "image_status": "highres_scan",
  "image_uris": {
    "small": "https://cards.scryfall.io/small/front/a/b/aba51852-af8f-49d8-8fb6-22d52a1742b8.jpg?1626097603",
    "normal": "https://cards.scryfall.io/normal/front/a/b/aba51852-af8f-49d8-8fb6-22d52a1742b8.jpg?1626097603",
    "large": "https://cards.scryfall.io/large/front/a/b/aba51852-af8f-49d8-8fb6-22d52a1742b8.jpg?1626097603",
    "png": "https://cards.scryfall.io/png/front/a/b/aba51852-af8f-49d8-8fb6-22d52a1742b8.png?1626097603",
    "art_crop": "https://cards.scryfall.io/art_crop/front/a/b/aba51852-af8f-49d8-8fb6-22d52a1742b8.jpg?1626097603",
    "border_crop": "https://cards.scryfall.io/border_crop/front/a/b/aba51852-af8f-49d8-8fb6-22d52a1742b8.jpg?1626097603"
  },
  "mana_cost": "{G}",
  "cmc": 1.0,
  "type_line": "Creature \u2014 Goblin Shaman",
  "oracle_text": "Exalted (Whenever a creature you control attacks alone, that creature gets +1/+1 until end of turn.)\n{T}: Add {B}, {R}, or {G}.",
  "power": "0",
  "toughness": "1",
  "colors": [
    "G"
  ],
  "color_identity": [
    "B",
    "G",
    "R"
  ],
  "keywords": [
    "Exalted"
  ],
  "produced_mana": [
    "B",
    "G",
    "R"
  ],
  "legalities": {
    "standard": "not_legal",
    "future": "not_legal",
    "historic": "not_legal",
    "timeless": "not_legal",
    "gladiator": "not_legal",
    "pioneer": "not_legal",
    "explorer": "not_legal",
    "modern": "legal",
    "legacy": "legal",
    "pauper": "not_legal",
    "vintage": "legal",
    "penny": "not_legal",
    "commander": "legal",
    "oathbreaker": "legal",
    "standardbrawl": "not_legal",
    "brawl": "not_legal",
    "alchemy": "not_legal",
    "paupercommander": "not_legal",
    "duel": "legal",
    "oldschool": "not_legal",
    "premodern": "not_legal",
    "predh": "not_legal"
  },
  "games": [
    "paper",
    "mtgo"
  ],
  "reserved": false,
  "game_changer": false,
  "foil": true,
  "nonfoil": true,
  "finishes": [
    "nonfoil",
    "foil"
  ],
  "oversized": false,
  "promo": false,
  "reprint": false,
  "variation": false,
  "set_id": "c1c7eb8c-f205-40ab-a609-767cb296544e",
  "set": "mh2",
  "set_name": "Modern Horizons 2",
  "set_type": "draft_innovation",
  "set_uri": "https://api.scryfall.com/sets/c1c7eb8c-f205-40ab-a609-767cb296544e",
  "set_search_uri": "https://api.scryfall.com/cards/search?order=set&q=e%3Amh2&unique=prints",
  "scryfall_set_uri": "https://scryfall.com/sets/mh2?utm_source=api",
  "rulings_uri": "https://api.scryfall.com/cards/aba51852-af8f-49d8-8fb6-22d52a1742b8/rulings",
  "prints_search_uri": "https://api.scryfall.com/cards/search?order=released&q=oracleid%3Ac8de43a3-ebd3-4000-b343-a6ffed11d34d&unique=prints",
  "collector_number": "166",
  "digital": false,
  "rarity": "rare",
  "flavor_text": "He protects the fetid bog from light, life, and the hideous sound of laughter.",
  "card_back_id": "0aeebaf5-8c7d-4636-9e82-8c27447861f7",
  "artist": "Mark Zug",
  "artist_ids": [
    "48e2b98c-5467-4671-bd42-4c3746115117"
  ],
  "illustration_id": "fe080227-e818-4278-abf3-10ef2601aba2",
  "border_color": "black",
  "frame": "2015",
  "security_stamp": "oval",
  "full_art": false,
  "textless": false,
  "booster": true,
  "story_spotlight": false,
  "edhrec_rank": 587,
  "preview": {
    "source": "Caleb Durward",
    "source_uri": "https://www.youtube.com/watch?v=d8c4iOjMMAA",
    "previewed_at": "2021-05-26"
  },
  "prices": {
    "usd": "1.07",
    "usd_foil": "3.43",
    "usd_etched": null,
    "eur": "1.56",
    "eur_foil": "3.76",
    "tix": "0.33"
  },
  "related_uris": {
    "gatherer": "https://gatherer.wizards.com/Pages/Card/Details.aspx?multiverseid=522242&printed=false",
    "tcgplayer_infinite_articles": "https://partner.tcgplayer.com/c/4931599/1830156/21018?subId1=api&trafcat=infinite&u=https%3A%2F%2Finfinite.tcgplayer.com%2Fsearch%3FcontentMode%3Darticle%26game%3Dmagic%26q%3DIgnoble%2BHierarch",
    "tcgplayer_infinite_decks": "https://partner.tcgplayer.com/c/4931599/1830156/21018?subId1=api&trafcat=infinite&u=https%3A%2F%2Finfinite.tcgplayer.com%2Fsearch%3FcontentMode%3Ddeck%26game%3Dmagic%26q%3DIgnoble%2BHierarch",
    "edhrec": "https://edhrec.com/route/?cc=Ignoble+Hierarch"
  },
  "purchase_uris": {
    "tcgplayer": "https://partner.tcgplayer.com/c/4931599/1830156/21018?subId1=api&u=https%3A%2F%2Fwww.tcgplayer.com%2Fproduct%2F239801%3Fpage%3D1",
    "cardmarket": "https://www.cardmarket.com/en/Magic/Products/Singles/Modern-Horizons-2/Ignoble-Hierarch?referrer=scryfall&utm_campaign=card_prices&utm_medium=text&utm_source=scryfall",
    "cardhoarder": "https://www.cardhoarder.com/cards/90709?affiliate_id=scryfall&ref=card-profile&utm_campaign=affiliate&utm_medium=card&utm_source=scryfall"
  }
}