{
  "object": "card",
  "id": "f6c8e0b5-218e-41dd-8b09-2d4aaec2c979",
  "oracle_id": "4c0a0448-b9d6-43a0-8549-64066dac63f0",
  "multiverse_ids": [
    650336
  ],
  "mtgo_id": 122632,
  "tcgplayer_id": 535809,
  "cardmarket_id": 753311,
  "name": "Talisman of Dominance",
  "lang": "en",
  "released_at": "2024-02-09",
  "uri": "https://api.scryfall.com/cards/f6c8e0b5-218e-41dd-8b09-2d4aaec2c979",
  "scryfall_uri": "https://scryfall.com/card/mkc/242/talisman-of-dominance?utm_source=api",
  "layout": "normal",
  "highres_image": true,
  "image_status": "highres_scan",
  "image_uris": {
    "small": "https://cards.scryfall.io/small/front/f/6/f6c8e0b5-218e-41dd-8b09-2d4aaec2c979.jpg?1706241098",
    "normal": "https://cards.scryfall.io/normal/front/f/6/f6c8e0b5-218e-41dd-8b09-2d4aaec2c979.jpg?1706241098",
    "large": "https://cards.scryfall.io/large/front/f/6/f6c8e0b5-218e-41dd-8b09-2d4aaec2c979.jpg?1706241098",
    "png": "https://cards.scryfall.io/png/front/f/6/f6c8e0b5-218e-41dd-8b09-2d4aaec2c979.png?1706241098",
    "art_crop": "https://cards.scryfall.io/art_crop/front/f/6/f6c8e0b5-218e-41dd-8b09-2d4aaec2c979.jpg?1706241098",
    "border_crop": "https://cards.scryfall.io/border_crop/front/f/6/f6c8e0b5-218e-41dd-8b09-2d4aaec2c979.jpg?1706241098"
  },
  "mana_cost": "{2}",
  "cmc": 2.0,
  "type_line": "Artifact",
  "oracle_text": "{T}: Add {C}.\n{T}: Add {U} or {B}. This artifact deals 1 damage to you.",
  "colors": [],
  "color_identity": [
    "B",
    "U"
  ],
  "keywords": [],
  "produced_mana": [
    "B",
    "C",
    "U"
  ],
  "legalities": {
    "standard": "not_legal",
    "future": "not_legal",
    "historic": "not_legal",
    "timeless": "not_legal",
    "gladiator": "not_legal",
    "pioneer": "not_legal",
    "explorer": "not_legal",
    "modern": "legal",
    "legacy": "legal",
    "pauper": "not_legal",
    "vintage": "legal",
    "penny": "not_legal",
    "commander": "legal",
    "oathbreaker": "legal",
    "standardbrawl": "not_legal",
    "brawl": "not_legal",
    "alchemy": "not_legal",
    "paupercommander": "not_legal",
    "duel": "legal",
    "oldschool": "not_legal",
    "premodern": "not_legal",
    "predh": "legal"
  },
  "games": [
    "paper",
    "mtgo"
  ],
  "reserved": false,
  "game_changer": false,
  "foil": false,
  "nonfoil": true,
  "finishes": [
    "nonfoil"
  ],
  "oversized": false,
  "promo": false,
  "reprint": true,
  "variation": false,
  "set_id": "286c37ca-ba65-4d3e-8c5d-d1878d88fd95",
  "set": "mkc",
  "set_name": "Murders at Karlov Manor Commander",
  "set_type": "commander",
  "set_uri": "https://api.scryfall.com/sets/286c37ca-ba65-4d3e-8c5d-d1878d88fd95",
  "set_search_uri": "https://api.scryfall.com/cards/search?order=set&q=e%3Amkc&unique=prints",
  "scryfall_set_uri": "https://scryfall.com/sets/mkc?utm_source=api",
  "rulings_uri": "https://api.scryfall.com/cards/f6c8e0b5-218e-41dd-8b09-2d4aaec2c979/rulings",
  "prints_search_uri": "https://api.scryfall.com/cards/search?order=released&q=oracleid%3A4c0a0448-b9d6-43a0-8549-64066dac63f0&unique=prints",
  "collector_number": "242",
  "digital": false,
  "rarity": "uncommon",
  "card_back_id": "0aeebaf5-8c7d-4636-9e82-8c27447861f7",
  "artist": "Mike Dringenberg",
  "artist_ids": [
    "a1407afa-0f54-43f8-938b-88b268074f91"
  ],
  "illustration_id": "b98f8e9b-d282-46ea-a3c7-025ffd69b05f",
  "border_color": "black",
  "frame": "2015",
  "full_art": false,
  "textless": false,
  "booster": false,
  "story_spotlight": false,
  "edhrec_rank": 95,
  "prices": {
    "usd": "0.75",
    "usd_foil": null,
    "usd_etched": null,
    "eur": "0.72",
    "eur_foil": null,
    "tix": "0.13"
  },
  "related_uris": {
    "gatherer": "https://gatherer.wizards.com/Pages/Card/Details.aspx?multiverseid=650336&printed=false",
    "tcgplayer_infinite_articles": "https://partner.tcgplayer.com/c/4931599/1830156/21018?subId1=api&trafcat=infinite&u=https%3A%2F%2Finfinite.tcgplayer.com%2Fsearch%3FcontentMode%3Darticle%26game%3Dmagic%26q%3DTalisman%2Bof%2BDominance",
    "tcgplayer_infinite_decks": "https://partner.tcgplayer.com/c/4931599/1830156/21018?subId1=api&trafcat=infinite&u=https%3A%2F%2Finfinite.tcgplayer.com%2Fsearch%3FcontentMode%3Ddeck%26game%3Dmagic%26q%3DTalisman%2Bof%2BDominance",
    "edhrec": "https://edhrec.com/route/?cc=Talisman+of+Dominance"
  },
  "purchase_uris": {
    "tcgplayer": "https://partner.tcgplayer.com/c/4931599/1830156/21018?subId1=api&u=https%3A%2F%2Fwww.tcgplayer.com%2Fproduct%2F535809%3Fpage%3D1",
    "cardmarket": "https://www.cardmarket.com/en/Magic/Products/Singles/Commander-Murders-at-Karlov-Manor/Talisman-of-Dominance?referrer=scryfall&utm_campaign=card_prices&utm_medium=text&utm_source=scryfall",
    "cardhoarder": "https://www.cardhoarder.com/cards/122632?affiliate_id=scryfall&ref=card-profile&utm_campaign=affiliate&utm_medium=card&utm_source=scryfall"
  }
}